aiotractive/__init__.py
aiotractive/api.py
aiotractive/channel.py
aiotractive/data_object.py
aiotractive/exceptions.py
aiotractive/trackable_object.py
aiotractive/tracker.py
aiotractive/tractive.py
aiotractive-0.7.0.dist-info/licenses/LICENSE
aiotractive-0.7.0.dist-info/METADATA
aiotractive-0.7.0.dist-info/WHEEL
aiotractive-0.7.0.dist-info/top_level.txt
aiotractive-0.7.0.dist-info/zip-safe
aiotractive-0.7.0.dist-info/RECORD
