Metadata-Version: 2.4
Name: aiotractive
Version: 0.7.0
Summary: Asynchronous Python client for the Tractive REST API
Home-page: https://github.com/zhulik/aiotractive
Author: Gleb Sinyavskiy
Author-email: zhulik.gleb@gmail.com
License: The MIT License
Keywords: tractive,rest,api,aio,async,await
Classifier: Development Status :: 3 - Alpha
Classifier: Intended Audience :: Developers
Classifier: Natural Language :: English
Classifier: License :: OSI Approved :: MIT License
Classifier: Programming Language :: Python :: 3.7
Classifier: Programming Language :: Python :: 3.8
Classifier: Programming Language :: Python :: 3.9
Classifier: Programming Language :: Python :: 3.10
License-File: LICENSE
Requires-Dist: aiohttp>=3.8.1
Requires-Dist: yarl>=1.7.2
Dynamic: author
Dynamic: author-email
Dynamic: classifier
Dynamic: description
Dynamic: description-content-type
Dynamic: home-page
Dynamic: keywords
Dynamic: license
Dynamic: license-file
Dynamic: requires-dist
Dynamic: summary
